robotnetwork-0.1.4.data/scripts/run_installer.bat
src/__init__.py
src/app.py
robotnetwork-0.1.4.dist-info/LICENSE
robotnetwork-0.1.4.dist-info/METADATA
robotnetwork-0.1.4.dist-info/WHEEL
robotnetwork-0.1.4.dist-info/entry_points.txt
robotnetwork-0.1.4.dist-info/top_level.txt
robotnetwork-0.1.4.dist-info/RECORD
