Metadata-Version: 2.1
Name: robotnetwork
Version: 0.1.4
Summary: A tool to relay http message from venus to slack.
Home-page: https://github.com/gorefbitim/robotnetwork
Author: Ofer Rahat
Author-email: leofer@gmail.com
Classifier: License :: OSI Approved :: GNU General Public License v3 (GPLv3)
Classifier: Operating System :: Microsoft :: Windows
Classifier: Operating System :: POSIX :: Linux
License-File: LICENSE
Requires-Dist: fastapi
Requires-Dist: uvicorn
Requires-Dist: requests
Requires-Dist: configparser
